llama_index/llms/vertex/__init__.py
llama_index/llms/vertex/base.py
llama_index/llms/vertex/gemini_utils.py
llama_index/llms/vertex/utils.py
llama_index_llms_vertex-0.6.1.dist-info/METADATA
llama_index_llms_vertex-0.6.1.dist-info/WHEEL
llama_index_llms_vertex-0.6.1.dist-info/licenses/LICENSE
llama_index_llms_vertex-0.6.1.dist-info/RECORD
