Metadata-Version: 2.4
Name: llama-index-llms-vertex
Version: 0.6.1
Summary: llama-index llms vertex integration
Author-email: Your Name <you@example.com>
License-Expression: MIT
License-File: LICENSE
Requires-Python: <4.0,>=3.9
Requires-Dist: google-cloud-aiplatform<2,>=1.39.0
Requires-Dist: llama-index-core<0.15,>=0.13.0
